visionmetrics/__init__.py
visionmetrics/prediction_filters.py
visionmetrics/caption/__init__.py
visionmetrics/caption/azure_openai_model_eval.py
visionmetrics/caption/azure_openai_model_eval_base.py
visionmetrics/caption/bleu.py
visionmetrics/caption/caption_eval_base.py
visionmetrics/caption/cider.py
visionmetrics/caption/coco_evalcap_utils.py
visionmetrics/caption/meteor.py
visionmetrics/caption/rougel.py
visionmetrics/classification/__init__.py
visionmetrics/classification/accuracy.py
visionmetrics/classification/common.py
visionmetrics/classification/precision_recall.py
visionmetrics/common/__init__.py
visionmetrics/common/utils.py
visionmetrics/detection/__init__.py
visionmetrics/detection/confusion_matrix.py
visionmetrics/detection/mean_ap.py
visionmetrics/grounding/__init__.py
visionmetrics/grounding/recall.py
visionmetrics/key_value_pair/__init__.py
visionmetrics/key_value_pair/key_value_pair_eval.py
visionmetrics/key_value_pair/key_value_pair_eval_base.py
visionmetrics/matting/__init__.py
visionmetrics/matting/boundary_foreground_iou.py
visionmetrics/matting/boundary_mean_iou.py
visionmetrics/matting/foreground_iou.py
visionmetrics/matting/l1_error.py
visionmetrics/matting/matting_eval_base.py
visionmetrics/matting/mean_iou.py
visionmetrics/regression/__init__.py
visionmetrics/regression/accuracy.py
visionmetrics/retrieval/__init__.py
visionmetrics/retrieval/precision_recall.py
visionmetrics/wrappers/__init__.py
visionmetrics-0.0.21.dist-info/licenses/LICENSE
visionmetrics-0.0.21.dist-info/METADATA
visionmetrics-0.0.21.dist-info/WHEEL
visionmetrics-0.0.21.dist-info/top_level.txt
visionmetrics-0.0.21.dist-info/RECORD
