Metadata-Version: 2.4
Name: visionmetrics
Version: 0.0.21
Summary: Evaluation metric codes for various vision tasks.
Home-page: https://github.com/microsoft/visionmetrics
Author: Microsoft
License: MIT
Requires-Python: >=3.10
License-File: LICENSE
Requires-Dist: numpy
Requires-Dist: torch
Requires-Dist: torchmetrics[detection]~=1.2.1
Requires-Dist: opencv-python-headless
Requires-Dist: Pillow>=6.2.2
Requires-Dist: irisml-tasks-azure-openai
Provides-Extra: caption
Requires-Dist: pycocoevalcap; extra == "caption"
Requires-Dist: pycocotools; extra == "caption"
Provides-Extra: dev
Requires-Dist: pre-commit; extra == "dev"
Requires-Dist: flake8; extra == "dev"
Requires-Dist: isort; extra == "dev"
Requires-Dist: pytest; extra == "dev"
Dynamic: license-file
